{
  "project_info": {
    "project_number": "38684885505",
    "firebase_url": "https://homecoco-beda7.firebaseio.com",
    "project_id": "homecoco-beda7",
    "storage_bucket": "homecoco-beda7.appspot.com"
  },
  "client": [
    {
      "client_info": {
        "mobilesdk_app_id": "1:38684885505:android:f6a4a61e4570a0c2",
        "android_client_info": {
          "package_name": "kr.o3selab.homecoco"
        }
      },
      "oauth_client": [
        {
          "client_id": "38684885505-ev38pp0kejt25614ic84sei73v22pmdh.apps.googleusercontent.com",
          "client_type": 3
        }
      ],
      "api_key": [
        {
          "current_key": "AIzaSyA7JsEXGBDhcte2CvMP9yjrLQirpIQxxCo"
        }
      ],
      "services": {
        "analytics_service": {
          "status": 1
        },
        "appinvite_service": {
          "status": 1,
          "other_platform_oauth_client": []
        },
        "ads_service": {
          "status": 2
        }
      }
    }
  ],
  "configuration_version": "1"
}